pyfolio/__init__.py
pyfolio/_version.py
pyfolio/capacity.py
pyfolio/deprecate.py
pyfolio/interesting_periods.py
pyfolio/ipycompat.py
pyfolio/perf_attrib.py
pyfolio/plot_cn_name_map.py
pyfolio/plotting.py
pyfolio/pos.py
pyfolio/round_trips.py
pyfolio/tears.py
pyfolio/timeseries.py
pyfolio/txn.py
pyfolio/utils.py
pyfolio_tej-2.0.4.dist-info/licenses/LICENSE
pyfolio_tej-2.0.4.dist-info/METADATA
pyfolio_tej-2.0.4.dist-info/WHEEL
pyfolio_tej-2.0.4.dist-info/top_level.txt
pyfolio_tej-2.0.4.dist-info/RECORD
