Metadata-Version: 2.4
Name: pyfolio-tej
Version: 2.0.4
Summary: Performance and risk analysis of financial portfolios with Python
Author: tej
Author-email: tej@tej.com.tw
Maintainer: tej api Development Team
Maintainer-email: tej@tej.com.tw
License: Apache-2.0
Project-URL: homepage, https://tquant.tejwin.com/
Project-URL: repository, https://github.com/tejtw/pyfolio-tej
Classifier: Development Status :: 4 - Beta
Classifier: License :: OSI Approved :: Apache Software License
Classifier: Natural Language :: English
Classifier: Programming Language :: Python
Classifier: Programming Language :: Python :: 3.8
Classifier: Programming Language :: Python :: 3.9
Classifier: Programming Language :: Python :: 3.10
Classifier: Programming Language :: Python :: 3.11
Classifier: Programming Language :: Python :: 3.12
Classifier: Operating System :: OS Independent
Classifier: Intended Audience :: Science/Research
Classifier: Topic :: Office/Business :: Financial :: Investment
Classifier: Topic :: Scientific/Engineering :: Information Analysis
Requires-Python: >=3.8
License-File: LICENSE
Requires-Dist: tqdm
Requires-Dist: scikit-learn
Requires-Dist: distributed
Requires-Dist: packaging
Provides-Extra: test
Requires-Dist: tox>=2.3.1; extra == "test"
Requires-Dist: coverage>=4.0.3; extra == "test"
Requires-Dist: coveralls==3.0.1; extra == "test"
Requires-Dist: pytest>=6.2; extra == "test"
Requires-Dist: pytest-xdist>=2.5.0; extra == "test"
Requires-Dist: pytest-cov>=2.12; extra == "test"
Requires-Dist: parameterized>=0.6.1; extra == "test"
Requires-Dist: flake8>=3.9.1; extra == "test"
Requires-Dist: black; extra == "test"
Provides-Extra: dev
Requires-Dist: flake8>=3.9.1; extra == "dev"
Requires-Dist: black; extra == "dev"
Requires-Dist: pre-commit>=2.12.1; extra == "dev"
Provides-Extra: docs
Requires-Dist: Cython; extra == "docs"
Requires-Dist: Sphinx>=1.3.2; extra == "docs"
Requires-Dist: numpydoc>=0.5.0; extra == "docs"
Requires-Dist: sphinx-autobuild>=0.6.0; extra == "docs"
Requires-Dist: pydata-sphinx-theme; extra == "docs"
Requires-Dist: sphinx-markdown-tables; extra == "docs"
Requires-Dist: sphinx_copybutton; extra == "docs"
Requires-Dist: m2r2; extra == "docs"
Dynamic: license-file
